Metadata-Version: 2.1
Name: cotiara
Version: 0.1.3
Summary: An interpreter written in Python for the Cotiara language
Author: dimabreus
Author-email: dmitriybreus5@gmail.com
Requires-Dist: keyboard
Requires-Dist: pyautogui
